hostlist/__init__.py
hostlist/addhost.py
hostlist/buildfiles.py
hostlist/cnamelist.py
hostlist/config.py
hostlist/daemon.py
hostlist/host.py
hostlist/hostlist.py
hostlist/output_services.py
hostlist/dnsvs/__init__.py
hostlist/dnsvs/sync.py
hostlist-1.4.9.dist-info/entry_points.txt
hostlist-1.4.9.dist-info/licenses/LICENSE
hostlist-1.4.9.dist-info/WHEEL
hostlist-1.4.9.dist-info/METADATA
hostlist-1.4.9.dist-info/RECORD
