Metadata-Version: 2.4
Name: hostlist
Version: 1.4.9
Summary: Sync hostlist and builds config files for services.
Home-page: https://github.com/particlekit/hostlist
Author: Robin Roth
Author-email: robin.roth@kit.edu
Requires-Python: >=3.2
Classifier: Development Status :: 4 - Beta
Classifier: License :: OSI Approved :: GNU General Public License v3 or later (GPLv3+)
Classifier: Environment :: Console
Classifier: Intended Audience :: System Administrators
Classifier: Operating System :: POSIX :: Linux
Classifier: Topic :: System :: Systems Administration
License-File: LICENSE
Requires-Dist: PyYAML
Requires-Dist: termcolor
Requires-Dist: requests
Requires-Dist: cherrypy
Requires-Dist: GitPython
Requires-Dist: ansible-cmdb
Requires-Dist: typing
